noexcept/__init__.py
noexcept/call.py
noexcept/exception.py
noexcept/module.py
noexcept/pathFinder.py
noexcept-1.5.4.dist-info/licenses/LICENSE
noexceptTestScript/__init__.py
noexcept-1.5.4.dist-info/METADATA
noexcept-1.5.4.dist-info/WHEEL
noexcept-1.5.4.dist-info/entry_points.txt
noexcept-1.5.4.dist-info/top_level.txt
noexcept-1.5.4.dist-info/RECORD
