Metadata-Version: 2.4
Name: noexcept
Version: 1.5.4
Summary: A callable interface for structured exceptions
Author: Nichola Walch
Author-email: Nichola Walch <littler.compression@gmail.com>
License: MIT
Requires-Python: >=3.8
License-File: LICENSE
Requires-Dist: exceptiongroup; python_version < "3.11"
Requires-Dist: rememory
Dynamic: author
Dynamic: license-file
Dynamic: requires-python
